nvmdeploy/__init__.py
nvmdeploy/fastinit.py
nvmdeploy/nevermore.py
nvmdeploy/nvmjenkins.py
nvmdeploy-0.7.dist-info/DESCRIPTION.rst
nvmdeploy-0.7.dist-info/METADATA
nvmdeploy-0.7.dist-info/RECORD
nvmdeploy-0.7.dist-info/WHEEL
nvmdeploy-0.7.dist-info/entry_points.txt
nvmdeploy-0.7.dist-info/metadata.json
nvmdeploy-0.7.dist-info/top_level.txt
nvmdeploy-0.7.dist-info/zip-safe
nvmdeploysrc/__init__.py
nvmdeploysrc/fastinit.py
nvmdeploysrc/nevermore.py
nvmdeploysrc/nvmjenkins.py
nvmdeploysrc/templates.py
nvmdeploysrc/testing.py
