Metadata-Version: 2.0
Name: nvmdeploy
Version: 0.7
Summary: fast release pod tool
Home-page: https://git.elenet.me/zhilong.wang/nvmdeploy
Author: stephenw
Author-email: zhilong.wang@ele.me
License: MIT
Keywords: pod release
Platform: UNKNOWN
Requires-Dist: PyYAML
Requires-Dist: python-jenkins
Requires-Dist: six
Requires-Dist: pbr
Requires-Dist: multi-key-dict
